planet/__init__.py
planet/assignment.py
planet/bitvector.py
planet/block.py
planet/block_factor.py
planet/blocks.py
planet/candl.py
planet/condition.py
planet/constraint.py
planet/constraint_manager.py
planet/cross.py
planet/design.py
planet/design_exceptions.py
planet/design_helpers.py
planet/design_variable.py
planet/designer.py
planet/formatter.py
planet/groups.py
planet/helpers.py
planet/logger.py
planet/narray.py
planet/nest.py
planet/old.py
planet/orders.py
planet/participants.py
planet/plans.py
planet/randomizer.py
planet/replications.py
planet/solver.py
planet/unit.py
planet/variable.py
planet_dsl-1.0.1.dist-info/licenses/LICENSE
planet_dsl-1.0.1.dist-info/METADATA
planet_dsl-1.0.1.dist-info/WHEEL
planet_dsl-1.0.1.dist-info/top_level.txt
planet_dsl-1.0.1.dist-info/RECORD
