Metadata-Version: 2.4
Name: planet-dsl
Version: 1.0.1
Summary: A DSL for defining experimental designs
Author: London Bielicke
License-File: LICENSE
Requires-Dist: bitarray==2.9.3
Requires-Dist: bitstring==4.2.3
Requires-Dist: contourpy==1.3.1
Requires-Dist: cycler==0.12.1
Requires-Dist: duckdb==1.1.3
Requires-Dist: fonttools==4.55.3
Requires-Dist: Jinja2==3.1.6
Requires-Dist: kiwisolver==1.4.7
Requires-Dist: lark==1.2.2
Requires-Dist: MarkupSafe==3.0.2
Requires-Dist: matplotlib==3.10.0
Requires-Dist: numpy==2.1.2
Requires-Dist: packaging==24.2
Requires-Dist: pandas==2.2.3
Requires-Dist: pillow==11.0.0
Requires-Dist: pyparsing==3.2.0
Requires-Dist: python-dateutil==2.9.0.post0
Requires-Dist: pytz==2025.2
Requires-Dist: six==1.17.0
Requires-Dist: tzdata==2025.2
Requires-Dist: z3-solver==4.13.3.0
Dynamic: author
Dynamic: license-file
Dynamic: requires-dist
Dynamic: summary
